LICENSE
MANIFEST.in
README
setup.cfg
setup.py
Flask_Static.egg-info/PKG-INFO
Flask_Static.egg-info/SOURCES.txt
Flask_Static.egg-info/dependency_links.txt
Flask_Static.egg-info/namespace_packages.txt
Flask_Static.egg-info/not-zip-safe
Flask_Static.egg-info/requires.txt
Flask_Static.egg-info/top_level.txt
docs/conf.py
docs/index.rst
docs/_themes/.gitignore
docs/_themes/LICENSE
docs/_themes/README
docs/_themes/flask_theme_support.py
docs/_themes/flask/layout.html
docs/_themes/flask/relations.html
docs/_themes/flask/theme.conf
docs/_themes/flask/static/flasky.css_t
docs/_themes/flask/static/small_flask.css
docs/_themes/flask_small/layout.html
docs/_themes/flask_small/theme.conf
docs/_themes/flask_small/static/flasky.css_t
flaskext/__init__.py
flaskext/static.py